plsfix-0.1.8.dist-info/METADATA
plsfix-0.1.8.dist-info/WHEEL
plsfix/__init__.py
plsfix/__init__.pyi
plsfix/py.typed
plsfix/plsfix.cpython-313-aarch64-linux-gnu.so
plsfix-0.1.8.dist-info/RECORD
